litenn/__init__.py
litenn/core/CLKernelHelper.py
litenn/core/Cacheton.py
litenn/core/Saveable.py
litenn/core/Tensor.py
litenn/core/TensorAxes.py
litenn/core/TensorShape.py
litenn/core/__init__.py
litenn/core/backward.py
litenn/core/hint/__init__.py
litenn/core/info/InfoBroadcast.py
litenn/core/info/InfoConcat.py
litenn/core/info/InfoConv2D.py
litenn/core/info/InfoConvAxis.py
litenn/core/info/InfoReduction.py
litenn/core/info/InfoReshape.py
litenn/core/info/InfoStack.py
litenn/core/info/InfoTile.py
litenn/core/info/InfoTranspose.py
litenn/core/info/__init__.py
litenn/core/initializer/CoordsArange.py
litenn/core/initializer/Glorot.py
litenn/core/initializer/He.py
litenn/core/initializer/Initializer.py
litenn/core/initializer/MeshGrid2D.py
litenn/core/initializer/NumpyArray.py
litenn/core/initializer/RandomNormal.py
litenn/core/initializer/RandomUniform.py
litenn/core/initializer/Scalar.py
litenn/core/initializer/__init__.py
litenn/core/minicl/CLBuffer.py
litenn/core/minicl/CLDevice.py
litenn/core/minicl/CLDevicesBuffers.py
litenn/core/minicl/CLKernel.py
litenn/core/minicl/CLShallowMode.py
litenn/core/minicl/__init__.py
litenn/core/minicl/devices.py
litenn/core/minicl/api/OpenCL/OpenCL.py
litenn/core/minicl/api/OpenCL/__init__.py
litenn/core/module/AdaptiveInstanceNorm2D.py
litenn/core/module/BatchNorm2D.py
litenn/core/module/BlurPool.py
litenn/core/module/Conv2D.py
litenn/core/module/Conv2DTranspose.py
litenn/core/module/Dense.py
litenn/core/module/DenseAffine.py
litenn/core/module/DepthwiseConv2D.py
litenn/core/module/Dropout.py
litenn/core/module/FRNorm2D.py
litenn/core/module/InstanceNorm2D.py
litenn/core/module/Module.py
litenn/core/module/ModuleBase.py
litenn/core/module/PReLU.py
litenn/core/module/SeparableConv2D.py
litenn/core/module/TLU.py
litenn/core/op/__init__.py
litenn/core/op/concat.py
litenn/core/op/conv2D.py
litenn/core/op/conv2DTranspose.py
litenn/core/op/depthwise_conv2D.py
litenn/core/op/dropout.py
litenn/core/op/dual_wise_op.py
litenn-2020.11.230.dist-info/LICENSE
litenn-2020.11.230.dist-info/METADATA
litenn-2020.11.230.dist-info/WHEEL
litenn-2020.11.230.dist-info/top_level.txt
litenn-2020.11.230.dist-info/RECORD
