Metadata-Version: 2.1
Name: litenn
Version: 2020.11.230
Summary: Lightweight machine learning library based on OpenCL 1.2
Home-page: https://github.com/iperov/litenn
Author: iperov
Author-email: lepersorium@gmail.com
License: MIT
Platform: UNKNOWN
Classifier: License :: OSI Approved :: MIT License
Classifier: Operating System :: OS Independent
Classifier: Programming Language :: Python :: 3
Classifier: Environment :: GPU
Classifier: Topic :: Scientific/Engineering
Requires-Python: >=3.6
Requires-Dist: numpy
